audiolibrarian/__init__.py
audiolibrarian/audiosource.py
audiolibrarian/base.py
audiolibrarian/commands.py
audiolibrarian/config.py
audiolibrarian/genremanager.py
audiolibrarian/musicbrainz.py
audiolibrarian/normalizer.py
audiolibrarian/output.py
audiolibrarian/records.py
audiolibrarian/sh.py
audiolibrarian/text.py
audiolibrarian/audiofile/__init__.py
audiolibrarian/audiofile/audiofile.py
audiolibrarian/audiofile/tags.py
audiolibrarian/audiofile/formats/__init__.py
audiolibrarian/audiofile/formats/flac.py
audiolibrarian/audiofile/formats/m4a.py
audiolibrarian/audiofile/formats/mp3.py
audiolibrarian/entrypoints/__init__.py
audiolibrarian/entrypoints/cli.py
audiolibrarian/templates/config.toml
picard_src/README.md
picard_src/__init__.py
picard_src/textencoding.py
audiolibrarian-0.18.0.dist-info/METADATA
audiolibrarian-0.18.0.dist-info/WHEEL
audiolibrarian-0.18.0.dist-info/entry_points.txt
audiolibrarian-0.18.0.dist-info/licenses/COPYING
audiolibrarian-0.18.0.dist-info/licenses/LICENSE
audiolibrarian-0.18.0.dist-info/RECORD
