Metadata-Version: 2.4
Name: audiolibrarian
Version: 0.18.0
Summary: Manage my audio library.
Project-URL: Repository, https://github.com/toadstule/audiolibrarian
Author-email: Steve Jibson <steve@jibson.com>
License-File: COPYING
License-File: LICENSE
Classifier: Development Status :: 4 - Beta
Classifier: License :: OSI Approved :: GNU General Public License v3 (GPLv3)
Classifier: Programming Language :: Python
Requires-Python: <3.14,>=3.12
Requires-Dist: ansicolors
Requires-Dist: discid
Requires-Dist: ffmpeg-normalize
Requires-Dist: filelock
Requires-Dist: fuzzywuzzy
Requires-Dist: musicbrainzngs
Requires-Dist: mutagen
Requires-Dist: pydantic-settings
Requires-Dist: python-levenshtein
Requires-Dist: pyyaml
Requires-Dist: requests
Requires-Dist: xdg-base-dirs
